datafushion_plugins_sparkpy-1.0.7.data/data/README.md
datafushion_spark/__init__.py
datafushion_spark/handle.py
datafushion_spark/version.py
datafushion_plugins_sparkpy-1.0.7.dist-info/METADATA
datafushion_plugins_sparkpy-1.0.7.dist-info/WHEEL
datafushion_plugins_sparkpy-1.0.7.dist-info/entry_points.txt
datafushion_plugins_sparkpy-1.0.7.dist-info/top_level.txt
datafushion_plugins_sparkpy-1.0.7.dist-info/zip-safe
datafushion_plugins_sparkpy-1.0.7.dist-info/RECORD
