Metadata-Version: 2.1
Name: datafushion-plugins-sparkpy
Version: 1.0.7
Summary: DataFushion的SparkPy算法插件
Home-page: UNKNOWN
Author: 肖林朋
Author-email: 1553990434@qq.com
License: XiaoLinpeng Licence
Platform: any
Requires-Dist: datafushion-plugins-python
Requires-Dist: pyspark2pmml
